<?xml version="1.0" encoding="utf-8" ?>
<dwsync>
<file name="api.php" server="173.201.97.128" local="129582282600000000" remote="129582282600000000" />
<file name="readme.txt" server="173.201.97.128" local="129582282600000000" remote="129582282600000000" />
<file name="sample_functions_for_theme.php" server="173.201.97.128" local="129582282600000000" remote="129582282600000000" />
<file name="styles-with-shortcodes-theme.php" server="173.201.97.128" local="129582282600000000" remote="129582282600000000" />
<file name="styles-with-shortcodes.php" server="173.201.97.128" local="129582282600000000" remote="129582282600000000" />
<file name="api.php" server="72.167.232.191" local="129582318600000000" remote="129776472600000000" />
<file name="readme.txt" server="72.167.232.191" local="129776475600000000" remote="129776475600000000" />
<file name="sample_functions_for_theme.php" server="72.167.232.191" local="129776475600000000" remote="129776475600000000" />
<file name="styles-with-shortcodes-theme.php" server="72.167.232.191" local="129776475600000000" remote="129776475600000000" />
<file name="styles-with-shortcodes.php" server="72.167.232.191" local="129776475600000000" remote="129776475600000000" />
</dwsync>