<?xml version="1.0" encoding="utf-8" ?>
<dwsync>
<file name="extra_image_processing.php" server="72.167.232.191" local="129773935800000000" remote="129773935800000000" />
<file name="gold_cart_readme.txt" server="72.167.232.191" local="129773935800000000" remote="129773935800000000" />
<file name="gold_options.php" server="72.167.232.191" local="129773935800000000" remote="129773935800000000" />
<file name="gold_shopping_cart.php" server="72.167.232.191" local="129773935800000000" remote="129773935800000000" />
<file name="grid_display_functions.php" server="72.167.232.191" local="129773935800000000" remote="129773935800000000" />
<file name="license.txt" server="72.167.232.191" local="129773935800000000" remote="129773935800000000" />
<file name="readme.txt" server="72.167.232.191" local="129773935800000000" remote="129773935800000000" />
<file name="upgrade_panel.php" server="72.167.232.191" local="129773935800000000" remote="129773935800000000" />
</dwsync>